vtmm/__init__.py
vtmm/const.py
vtmm/fresnel.py
vtmm/tmm.py
vtmm-0.1.dist-info/LICENSE
vtmm-0.1.dist-info/METADATA
vtmm-0.1.dist-info/WHEEL
vtmm-0.1.dist-info/top_level.txt
vtmm-0.1.dist-info/RECORD
