Metadata-Version: 2.1
Name: vtmm
Version: 0.1
Summary: Vectorized transfer matrix method (TMM) for computing the optical reflection and transmission of multilayer planar stacks
Home-page: https://github.com/fancompute/vtmm
Author: Ian Williamson
Author-email: ian.williamson@ieee.org
License: MIT
Platform: UNKNOWN
Classifier: Programming Language :: Python :: 3
Classifier: License :: OSI Approved :: MIT License
Classifier: Operating System :: OS Independent
Requires-Dist: tensorflow (>2.0)
Requires-Dist: numpy (>=1.16)
